MANIFEST.in
README.md
setup.py
chunked_uploads/__init__.py
chunked_uploads/admin.py
chunked_uploads/models.py
chunked_uploads/urls.py
chunked_uploads/utils.py
chunked_uploads/views.py
chunked_uploads/static/chunked_uploads/js/jquery.chunked_uploads.js
chunked_uploads/static/chunked_uploads/js/jquery.fileupload.js
chunked_uploads/static/chunked_uploads/js/jquery.iframe-transport.js
chunked_uploads/static/chunked_uploads/js/jquery.postmessage-transport.js
chunked_uploads/static/chunked_uploads/js/jquery.ui.widget.js
chunked_uploads/static/chunked_uploads/js/jquery.xdr-transport.js
chunked_uploads/static/chunked_uploads/js/progress.js
django_chunked_uploads.egg-info/PKG-INFO
django_chunked_uploads.egg-info/SOURCES.txt
django_chunked_uploads.egg-info/dependency_links.txt
django_chunked_uploads.egg-info/not-zip-safe
django_chunked_uploads.egg-info/top_level.txt